odoo/addons/ssi_property_management_stock/README.rst
odoo/addons/ssi_property_management_stock/__init__.py
odoo/addons/ssi_property_management_stock/__manifest__.py
odoo/addons/ssi_property_management_stock/models/__init__.py
odoo/addons/ssi_property_management_stock/models/property_object.py
odoo/addons/ssi_property_management_stock/static/description/icon.png
odoo/addons/ssi_property_management_stock/static/description/risk-assessment-template.odt
odoo/addons/ssi_property_management_stock/views/property_object_views.xml
odoo14_addon_ssi_property_management_stock-14.0.1.0.0.dist-info/METADATA
odoo14_addon_ssi_property_management_stock-14.0.1.0.0.dist-info/WHEEL
odoo14_addon_ssi_property_management_stock-14.0.1.0.0.dist-info/top_level.txt
odoo14_addon_ssi_property_management_stock-14.0.1.0.0.dist-info/RECORD
